newd/__init__.py
newd/detector.py
newd/detector_utils.py
newd/image_utils.py
newd-0.0.4.dist-info/licenses/LICENSE.md
newd-0.0.4.dist-info/METADATA
newd-0.0.4.dist-info/WHEEL
newd-0.0.4.dist-info/top_level.txt
newd-0.0.4.dist-info/RECORD
