Metadata-Version: 2.4
Name: newd
Version: 0.0.4
Summary: Nudity detection through deep learning
Home-page: https://github.com/iBz-04/newd
Author: iBz-04
Author-email: issakaibrahimrayamah@gmail.com
License: GPL-3.0-or-later
Project-URL: Documentation, https://github.com/iBz-04/newd#readme
Project-URL: Source, https://github.com/iBz-04/newd
Project-URL: Tracker, https://github.com/iBz-04/newd/issues
Keywords: nsfw nudity detection computer vision ai
Classifier: License :: OSI Approved :: GNU General Public License v3 or later (GPLv3+)
Classifier: Development Status :: 3 - Alpha
Classifier: Intended Audience :: Developers
Classifier: Topic :: Multimedia :: Graphics :: Graphics Conversion
Classifier: Topic :: Software Development :: Libraries :: Python Modules
Classifier: Programming Language :: Python
Classifier: Programming Language :: Python :: 3
Classifier: Programming Language :: Python :: 3.7
Classifier: Programming Language :: Python :: 3.8
Classifier: Programming Language :: Python :: 3.9
Classifier: Programming Language :: Python :: 3.10
Classifier: Programming Language :: Python :: Implementation :: CPython
Classifier: Operating System :: OS Independent
Requires-Python: >=3.6.0
License-File: LICENSE.md
Requires-Dist: pillow
Requires-Dist: opencv-python-headless>=4.5.1.48
Requires-Dist: tqdm
Requires-Dist: scikit-image
Requires-Dist: onnxruntime
Provides-Extra: dev
Requires-Dist: check-manifest; extra == "dev"
Requires-Dist: twine; extra == "dev"
Requires-Dist: wheel; extra == "dev"
Requires-Dist: build; extra == "dev"
Provides-Extra: test
Requires-Dist: pytest; extra == "test"
Requires-Dist: coverage; extra == "test"
Dynamic: author
Dynamic: author-email
Dynamic: classifier
Dynamic: description
Dynamic: description-content-type
Dynamic: home-page
Dynamic: keywords
Dynamic: license
Dynamic: license-file
Dynamic: project-url
Dynamic: provides-extra
Dynamic: requires-dist
Dynamic: requires-python
Dynamic: summary
